dagster_postgres_pandas/__init__.py
dagster_postgres_pandas/exceptions.py
dagster_postgres_pandas/io_manager.py
dagster_postgres_pandas/types.py
dagster_postgres_pandas-0.1.0.dist-info/METADATA
dagster_postgres_pandas-0.1.0.dist-info/WHEEL
dagster_postgres_pandas-0.1.0.dist-info/licenses/LICENSE
dagster_postgres_pandas-0.1.0.dist-info/RECORD
