Metadata-Version: 2.4
Name: dagster-postgres-pandas
Version: 0.1.0
Summary: PostgreSQL I/O manager for Dagster with Pandas DataFrame support
Project-URL: Homepage, https://github.com/klemensgraf/dagster-postgres-pandas
Project-URL: Documentation, https://github.com/klemensgraf/dagster-postgres-pandas/blob/main/README.md
Project-URL: Repository, https://github.com/klemensgraf/dagster-postgres-pandas.git
Project-URL: Bug Tracker, https://github.com/klemensgraf/dagster-postgres-pandas/issues
Project-URL: Changelog, https://github.com/klemensgraf/dagster-postgres-pandas/blob/main/CHANGELOG.md
Author-email: Klemens Graf <klemensgraf15@gmail.com>
Maintainer-email: Klemens Graf <klemensgraf15@gmail.com>
License-Expression: MIT
License-File: LICENSE
Keywords: dagster,data-engineering,io-manager,pandas,postgresql
Classifier: Development Status :: 3 - Alpha
Classifier: Intended Audience :: Developers
Classifier: Programming Language :: Python :: 3
Classifier: Programming Language :: Python :: 3.10
Classifier: Programming Language :: Python :: 3.11
Classifier: Programming Language :: Python :: 3.12
Classifier: Topic :: Database
Classifier: Topic :: Scientific/Engineering
Classifier: Topic :: Software Development :: Libraries :: Python Modules
Requires-Python: >=3.10
Requires-Dist: dagster>=1.8.0
Requires-Dist: pandas>=2.1.0
Requires-Dist: psycopg2-binary>=2.9.0
Requires-Dist: sqlalchemy>=2.0.25
Provides-Extra: dev
Requires-Dist: pytest-cov>=4.0.0; extra == 'dev'
Requires-Dist: pytest>=7.0.0; extra == 'dev'
Requires-Dist: ruff>=0.1.6; extra == 'dev'
Provides-Extra: docs
Requires-Dist: mkdocs-material>=8.5.0; extra == 'docs'
Requires-Dist: mkdocs-mermaid2-plugin>=0.6.0; extra == 'docs'
Requires-Dist: mkdocs>=1.4.0; extra == 'docs'
Provides-Extra: test
Requires-Dist: pytest-cov>=4.0.0; extra == 'test'
Requires-Dist: pytest>=7.0.0; extra == 'test'
